http_access
