Metadata-Version: 2.1
Name: http_access
Version: 0.1.3
Summary: http direct access django app
Home-page: https://github.com/EOxServer/http_access
Author: Nikola Jankovic
Author-email: nikola.jankovic@eox.at
License: UNKNOWN
Platform: UNKNOWN
Classifier: Programming Language :: Python :: 3
Classifier: License :: OSI Approved :: MIT License
Classifier: Operating System :: OS Independent
Requires-Python: >=3.6
